barebonesbot
