Metadata-Version: 1.1
Name: barebonesbot
Version: 0.3
Summary: A configurable Twitter-bot
Home-page: https://www.github.com/emanjavacas/barebonesbot/
Author: Enrique Manjavacas
Author-email: enrique.manjavacas@gmail.com
License: MIT
Download-URL: https://api.github.com/repos/emanjavacas/barebonesbot/tarball
Platform: UNKNOWN
